mcp_jenkins/__init__.py
mcp_jenkins/jenkins/__init__.py
mcp_jenkins/jenkins/_build.py
mcp_jenkins/jenkins/_client.py
mcp_jenkins/jenkins/_job.py
mcp_jenkins/jenkins/_node.py
mcp_jenkins/jenkins/_queue_item.py
mcp_jenkins/models/build.py
mcp_jenkins/models/job.py
mcp_jenkins/models/node.py
mcp_jenkins/models/queue_item.py
mcp_jenkins/server/__init__.py
mcp_jenkins/server/build.py
mcp_jenkins/server/job.py
mcp_jenkins/server/node.py
mcp_jenkins/server/queue_item.py
mcp_jenkins_fork-0.3.7.dist-info/licenses/LICENSE
mcp_jenkins_fork-0.3.7.dist-info/METADATA
mcp_jenkins_fork-0.3.7.dist-info/WHEEL
mcp_jenkins_fork-0.3.7.dist-info/entry_points.txt
mcp_jenkins_fork-0.3.7.dist-info/top_level.txt
mcp_jenkins_fork-0.3.7.dist-info/RECORD
