Metadata-Version: 2.4
Name: mcp-jenkins-fork
Version: 0.3.7
Summary: A fork of lanbaoshen/mcp-jenkins. See original at https://github.com/lanbaoshen/mcp-jenkins.
Author-email: lanbaoshen <lanbaoshen@icloud.com>
Maintainer-email: Dahyun Hong <dahyun.hong@dematic.com>
Requires-Python: >=3.10
License-File: LICENSE
Requires-Dist: mcp>=1.6.0
Requires-Dist: pydantic>=2.11.1
Requires-Dist: python-jenkins>=1.8.2
Requires-Dist: beautifulsoup4>=4.12.2
Dynamic: license-file
